{
  "VG_BEE": {
    "earned": true,
    "earned_time": 1687190301
  },
  "VG_CAMERA": {
    "earned": true,
    "earned_time": 1687443872
  },
  "VG_DAY1": {
    "earned": true,
    "earned_time": 1686673299
  },
  "VG_DAY2": {
    "earned": true,
    "earned_time": 1687019009
  },
  "VG_DAY76": {
    "earned": true,
    "earned_time": 1687189113
  },
  "VG_DAY77": {
    "earned": true,
    "earned_time": 1687191876
  },
  "VG_DAY79": {
    "earned": true,
    "earned_time": 1687379213
  },
  "VG_OLSHOSHONE": {
    "earned": true,
    "earned_time": 1687443404
  },
  "VG_RACCOONATTACK": {
    "earned": true,
    "earned_time": 1687443639
  },
  "VG_TURTLE": {
    "earned": true,
    "earned_time": 1686674136
  }
}