{
    "CODA_ACHIEVEMENT_001": {
    "earned": true,
    "earned_time": 1676717880
  },
    "CODA_ACHIEVEMENT_003": {
    "earned": true,
    "earned_time": 1676808904
  },
    "CODA_ACHIEVEMENT_006": {
    "earned": false,
    "earned_time": 0
  },
    "CODA_ACHIEVEMENT_010": {
    "earned": false,
    "earned_time": 0
  },
    "CODA_ACHIEVEMENT_013": {
    "earned": false,
    "earned_time": 0
  },
    "CODA_ACHIEVEMENT_015": {
    "earned": false,
    "earned_time": 0
  },
    "CODA_ACHIEVEMENT_016": {
    "earned": false,
    "earned_time": 0
  },
    "CODA_ACHIEVEMENT_017": {
    "earned": false,
    "earned_time": 0
  },
    "CODA_ACHIEVEMENT_019": {
    "earned": false,
    "earned_time": 0
  },
    "CODA_ACHIEVEMENT_021": {
    "earned": false,
    "earned_time": 0
  },
    "CODA_ACHIEVEMENT_022": {
    "earned": false,
    "earned_time": 0
  },
    "CODA_ACHIEVEMENT_023": {
    "earned": false,
    "earned_time": 0
  },
    "CODA_ACHIEVEMENT_024": {
    "earned": false,
    "earned_time": 0
  },
    "CODA_ACHIEVEMENT_025": {
    "earned": false,
    "earned_time": 0
  },
    "CODA_ACHIEVEMENT_026": {
    "earned": false,
    "earned_time": 0
  },
    "CODA_ACHIEVEMENT_027": {
    "earned": false,
    "earned_time": 0
  },
    "CODA_ACHIEVEMENT_028": {
    "earned": false,
    "earned_time": 0
  },
    "CODA_ACHIEVEMENT_029": {
    "earned": false,
    "earned_time": 0
  },
    "CODA_ACHIEVEMENT_030": {
    "earned": false,
    "earned_time": 0
  },
    "CODA_ACHIEVEMENT_031": {
    "earned": false,
    "earned_time": 0
  },
    "CODA_ACHIEVEMENT_032": {
    "earned": false,
    "earned_time": 0
  },
    "CODA_ACHIEVEMENT_035": {
    "earned": false,
    "earned_time": 0
  },
    "CODA_ACHIEVEMENT_037": {
    "earned": false,
    "earned_time": 0
  },
    "CODA_ACHIEVEMENT_038": {
    "earned": false,
    "earned_time": 0
  },
    "CODA_ACHIEVEMENT_039": {
    "earned": false,
    "earned_time": 0
  },
    "CODA_ACHIEVEMENT_040": {
    "earned": false,
    "earned_time": 0
  },
    "CODA_ACHIEVEMENT_041": {
    "earned": false,
    "earned_time": 0
  },
    "CODA_ACHIEVEMENT_042": {
    "earned": false,
    "earned_time": 0
  },
    "CODA_ACHIEVEMENT_043": {
    "earned": false,
    "earned_time": 0
  },
    "CODA_ACHIEVEMENT_044": {
    "earned": false,
    "earned_time": 0
  },
    "CODA_ACHIEVEMENT_045": {
    "earned": false,
    "earned_time": 0
  },
    "CODA_ACHIEVEMENT_046": {
    "earned": false,
    "earned_time": 0
  },
    "CODA_ACHIEVEMENT_047": {
    "earned": false,
    "earned_time": 0
  },
    "CODA_ACHIEVEMENT_048": {
    "earned": false,
    "earned_time": 0
  },
    "CODA_ACHIEVEMENT_049": {
    "earned": false,
    "earned_time": 0
  },
    "CODA_ACHIEVEMENT_050": {
    "earned": false,
    "earned_time": 0
  },
    "CODA_ACHIEVEMENT_051": {
    "earned": false,
    "earned_time": 0
  },
    "CODA_ACHIEVEMENT_052": {
    "earned": false,
    "earned_time": 0
  },
    "CODA_ACHIEVEMENT_053": {
    "earned": false,
    "earned_time": 0
  },
    "CODA_ACHIEVEMENT_054": {
    "earned": false,
    "earned_time": 0
  },
    "CODA_ACHIEVEMENT_055": {
    "earned": false,
    "earned_time": 0
  },
    "CODA_ACHIEVEMENT_056": {
    "earned": false,
    "earned_time": 0
  },
    "CODA_ACHIEVEMENT_057": {
    "earned": false,
    "earned_time": 0
  },
    "CODA_ACHIEVEMENT_058": {
    "earned": false,
    "earned_time": 0
  },
    "CODA_ACHIEVEMENT_059": {
    "earned": false,
    "earned_time": 0
  },
    "CODA_ACHIEVEMENT_060": {
    "earned": false,
    "earned_time": 0
  },
    "CODA_ACHIEVEMENT_061": {
    "earned": false,
    "earned_time": 0
  },
    "CODA_ACHIEVEMENT_062": {
    "earned": false,
    "earned_time": 0
  },
    "CODA_ACHIEVEMENT_063": {
    "earned": false,
    "earned_time": 0
  },
    "CODA_ACHIEVEMENT_064": {
    "earned": false,
    "earned_time": 0
  },
    "CODA_ACHIEVEMENT_081": {
    "earned": false,
    "earned_time": 0
  },
    "CODA_DLC_ACHIEVEMENT_001": {
    "earned": false,
    "earned_time": 0
  },
    "CODA_DLC_ACHIEVEMENT_002": {
    "earned": false,
    "earned_time": 0
  },
    "CODA_DLC_ACHIEVEMENT_003": {
    "earned": false,
    "earned_time": 0
  },
    "CODA_DLC_ACHIEVEMENT_004": {
    "earned": false,
    "earned_time": 0
  },
    "CODA_DLC_ACHIEVEMENT_005": {
    "earned": false,
    "earned_time": 0
  },
    "CODA_DLC_ACHIEVEMENT_006": {
    "earned": false,
    "earned_time": 0
  },
    "CODA_DLC_ACHIEVEMENT_007": {
    "earned": false,
    "earned_time": 0
  },
    "CODA_DLC_ACHIEVEMENT_008": {
    "earned": false,
    "earned_time": 0
  },
    "CODA_DLC_ACHIEVEMENT_009": {
    "earned": false,
    "earned_time": 0
  },
    "CODA_DLC_ACHIEVEMENT_010": {
    "earned": false,
    "earned_time": 0
  }
}